yasik/__init__.py
yasik/yasik_exe.py
yasik/yasik_interpreter.py
yasik-0.1.0.dist-info/LICENSE
yasik-0.1.0.dist-info/METADATA
yasik-0.1.0.dist-info/WHEEL
yasik-0.1.0.dist-info/RECORD
