Metadata-Version: 2.1
Name: yasik
Version: 0.1.0
Summary: 
Author: Ruslan Shaiakhmetov
Author-email: ruslan.shaiakhmetov@unibo.it
Requires-Python: >=3.9.13,<4.0.0
Classifier: Programming Language :: Python :: 3
Classifier: Programming Language :: Python :: 3.10
Classifier: Programming Language :: Python :: 3.11
Classifier: Programming Language :: Python :: 3.12
Requires-Dist: antlr4-python3-runtime (==4.13.1)
Requires-Dist: flake8 (==7.0.0)
Requires-Dist: numpy (>=1.26.2,<2.0.0)
Requires-Dist: pytest (>=7.4.3,<8.0.0)
Requires-Dist: pyyaml (>=6.0.1,<7.0.0)
Requires-Dist: treelib (>=1.7.0,<2.0.0)
Requires-Dist: twine (>=4.0.2,<5.0.0)
